submitter/__init__.py
submitter/client.py
submitter/model.py
submitter/adapters/__init__.py
submitter/adapters/weibo.py
post_submitter-0.7.2.dist-info/LICENSE
post_submitter-0.7.2.dist-info/METADATA
post_submitter-0.7.2.dist-info/WHEEL
post_submitter-0.7.2.dist-info/top_level.txt
post_submitter-0.7.2.dist-info/RECORD
