Metadata-Version: 2.1
Name: post-submitter
Version: 0.7.2
Summary: 基于 webhook 的博文提交器
Home-page: https://github.com/Drelf2018/submitter
Author: Drelf2018
Author-email: drelf2018@outlook.com
License: MIT
Keywords: python,weibo,webhook
Platform: UNKNOWN
Classifier: Development Status :: 1 - Planning
Classifier: Intended Audience :: Developers
Classifier: Programming Language :: Python :: 3
Classifier: Operating System :: Unix
Classifier: Operating System :: MacOS :: MacOS X
Classifier: Operating System :: Microsoft :: Windows
Requires-Python: >=3.8
Requires-Dist: APScheduler==3.10.4
Requires-Dist: httpx==0.28.0
Requires-Dist: loguru==0.7.2
Requires-Dist: Pillow==11.0.0
Requires-Dist: pydantic==2.10.2
